pandora_cloud/__init__.py
pandora_cloud/py.typed
pandora_cloud/server.py
pandora_cloud/flask/static/apple-touch-icon.png
pandora_cloud/flask/static/favicon-16x16.png
pandora_cloud/flask/static/favicon-32x32.png
pandora_cloud/flask/static/manifest.json
pandora_cloud/flask/static/service-worker.js
pandora_cloud/flask/static/_next/static/VkDNisWOezhjENf61sgQ1/buildManifest.js
pandora_cloud/flask/static/_next/static/VkDNisWOezhjENf61sgQ1/ssgManifest.js
pandora_cloud/flask/static/_next/static/chunks/1213-3a349d30aa6a72a3.js
pandora_cloud/flask/static/_next/static/chunks/1438-8d1de903270120c8.js
pandora_cloud/flask/static/_next/static/chunks/1564-77f6f9ff5dc52ea0.js
pandora_cloud/flask/static/_next/static/chunks/1724.7c86cd47cf0b0726.js
pandora_cloud/flask/static/_next/static/chunks/1966.293545626fb83130.js
pandora_cloud/flask/static/_next/static/chunks/1f110208-24bf6c2e080e0308.js
pandora_cloud/flask/static/_next/static/chunks/2104-09304abac0293deb.js
pandora_cloud/flask/static/_next/static/chunks/2186.470cc82a65d54ead.js
pandora_cloud/flask/static/_next/static/chunks/2357-96faabdfa8cc96a3.js
pandora_cloud/flask/static/_next/static/chunks/273.c06548dd1df12f14.js
pandora_cloud/flask/static/_next/static/chunks/2766-4b22cbefddaac9b3.js
pandora_cloud/flask/static/_next/static/chunks/3267-ff92f42a054abd60.js
pandora_cloud/flask/static/_next/static/chunks/3389-482943a0011c8266.js
pandora_cloud/flask/static/_next/static/chunks/3a34cc27-fd0458d5c342aa61.js
pandora_cloud/flask/static/_next/static/chunks/4099-9cd8db1fba82daf7.js
pandora_cloud/flask/static/_next/static/chunks/4137-447db6c53ca8543c.js
pandora_cloud/flask/static/_next/static/chunks/4184.6c7782ced6bdbb7f.js
pandora_cloud/flask/static/_next/static/chunks/5427-fa01eda28dd41717.js
pandora_cloud/flask/static/_next/static/chunks/6199c948-28b15521c4eb1cf7.js
pandora_cloud/flask/static/_next/static/chunks/6321.3b3b94262104b5a6.js
pandora_cloud/flask/static/_next/static/chunks/667-f735c0905709b955.js
Pandora_Cloud-0.7.3.dist-info/LICENSE
Pandora_Cloud-0.7.3.dist-info/METADATA
Pandora_Cloud-0.7.3.dist-info/WHEEL
Pandora_Cloud-0.7.3.dist-info/top_level.txt
Pandora_Cloud-0.7.3.dist-info/RECORD
